requests-stubs/METADATA.toml
requests-stubs/__init__.pyi
requests-stubs/__version__.pyi
requests-stubs/adapters.pyi
requests-stubs/api.pyi
requests-stubs/auth.pyi
requests-stubs/certs.pyi
requests-stubs/compat.pyi
requests-stubs/cookies.pyi
requests-stubs/exceptions.pyi
requests-stubs/help.pyi
requests-stubs/hooks.pyi
requests-stubs/models.pyi
requests-stubs/packages.pyi
requests-stubs/py.typed
requests-stubs/sessions.pyi
requests-stubs/status_codes.pyi
requests-stubs/structures.pyi
requests-stubs/utils.pyi
types_requests-2.32.0.20240914.dist-info/METADATA
types_requests-2.32.0.20240914.dist-info/WHEEL
types_requests-2.32.0.20240914.dist-info/top_level.txt
types_requests-2.32.0.20240914.dist-info/RECORD
